wizardwebssh/__init__.py
wizardwebssh/__main__.py
wizardwebssh/cli.py
wizardwebssh/handler.py
wizardwebssh/main.py
wizardwebssh/policy.py
wizardwebssh/settings.py
wizardwebssh/static/css/bootstrap.min.css
wizardwebssh/static/css/fonts/.gitignore
wizardwebssh/static/css/fullscreen.min.css
wizardwebssh/static/css/xterm.min.css
wizardwebssh/static/img/favicon.png
wizardwebssh/static/js/bootstrap.bundle.min.js
wizardwebssh/static/js/bootstrap.min.js
wizardwebssh/static/js/jquery.min.js
wizardwebssh/static/js/main.js
wizardwebssh/static/js/popper.min.js
wizardwebssh/static/js/xterm-addon-fit.min.js
wizardwebssh/static/js/xterm-addon-web-links.js
wizardwebssh/static/js/xterm.min.js
wizardwebssh/tabbedterminal.py
wizardwebssh/templates/index.html
wizardwebssh/utils.py
wizardwebssh/worker.py
wizardwebssh-1.9.3.dist-info/entry_points.txt
wizardwebssh-1.9.3.dist-info/LICENSE
wizardwebssh-1.9.3.dist-info/WHEEL
wizardwebssh-1.9.3.dist-info/METADATA
wizardwebssh-1.9.3.dist-info/RECORD
