Metadata-Version: 2.1
Name: wizardwebssh
Version: 1.9.3
Summary: Web based ssh client
Home-page: https://github.com/meramsey/wizardwebssh
License: MIT
Keywords: ssh,terminal,web,pyqt
Author: Michael Ramsey
Author-email: mike@hackerdise.me
Requires-Python: >=3.6.2,<4.0
Classifier: License :: OSI Approved :: MIT License
Classifier: Programming Language :: Python :: 3
Classifier: Programming Language :: Python :: 3.10
Classifier: Programming Language :: Python :: 3.7
Classifier: Programming Language :: Python :: 3.8
Classifier: Programming Language :: Python :: 3.9
Requires-Dist: PyQt5 (==5.15.6)
Requires-Dist: PyQt5-sip (==12.9.1)
Requires-Dist: PyQt5-stubs (==5.14.2.2)
Requires-Dist: PyQtWebEngine (==5.15.5)
Requires-Dist: paramiko (==2.10.1)
Requires-Dist: toml (==0.10.2)
Requires-Dist: tomlkit (==0.10.0)
Requires-Dist: tornado (==6.1)
Project-URL: Repository, https://github.com/meramsey/wizardwebssh
